task3/counter.sv
module counter #(
    parameter WIDTH = 8
)(
    input logic clk,
    input logic rst,
    input logic load_en,
    input logic [WIDTH-1:0] din,
    output logic [WIDTH-1:0] count
);

always_ff @(posedge clk) begin
    if (rst) 
        count <= {WIDTH{1'b0}};
    else if (load_en) 
        count <= din;
    else
        count <= count + {{WIDTH-1{1'b0}}, 1};
end

endmodule

task3/counter.vcd
$version Generated by VerilatedVcd $end
$date Tue Oct 25 14:48:14 2022 $end
$timescale 1ps $end

 $scope module TOP $end
  $var wire  1 # clk $end
  $var wire  8 ' count [7:0] $end
  $var wire  8 & din [7:0] $end
  $var wire  1 % load_en $end
  $var wire  1 $ rst $end
  $scope module counter $end
   $var wire 32 ( WIDTH [31:0] $end
   $var wire  1 # clk $end
   $var wire  8 ' count [7:0] $end
   $var wire  8 & din [7:0] $end
   $var wire  1 % load_en $end
   $var wire  1 $ rst $end
  $upscope $end
 $upscope $end
$enddefinitions $end


#0
0#
1$
0%
b00010011 &
b00000000 '
b00000000000000000000000000001000 (
#1
1#
#2
0#
#3
1#
#4
0#
0$
#5
1#
b00000001 '
#6
0#
#7
1#
b00000010 '
#8
0#
#9
1#
b00000011 '
#10
0#
#11
1#
b00000100 '
#12
0#
#13
1#
b00000101 '
#14
0#
#15
1#
b00000110 '
#16
0#
#17
1#
b00000111 '
#18
0#
#19
1#
b00001000 '
#20
0#
#21
1#
b00001001 '
#22
0#
#23
1#
b00001010 '
#24
0#
#25
1#
b00001011 '
#26
0#
#27
1#
b00001100 '
#28
0#
#29
1#
b00001101 '
#30
0#
#31
1#
b00001110 '
#32
0#
#33
1#
b00001111 '
#34
0#
#35
1#
b00010000 '
#36
0#
#37
1#
b00010001 '
#38
0#
#39
1#
b00010010 '
#40
0#
#41
1#
b00010011 '
#42
0#
#43
1#
b00010100 '
#44
0#
#45
1#
b00010101 '
#46
0#
#47
1#
b00010110 '
#48
0#
#49
1#
b00010111 '
#50
0#
#51
1#
b00011000 '
#52
0#
#53
1#
b00011001 '
#54
0#
#55
1#
b00011010 '
#56
0#
#57
1#
b00011011 '
#58
0#
#59
1#
b00011100 '
#60
0#
#61
1#
b00011101 '
#62
0#
#63
1#
b00011110 '
#64
0#
#65
1#
b00011111 '
#66
0#
#67
1#
b00100000 '
#68
0#
#69
1#
b00100001 '
#70
0#
#71
1#
b00100010 '
#72
0#
#73
1#
b00100011 '
#74
0#
#75
1#
b00100100 '
#76
0#
#77
1#
b00100101 '
#78
0#
#79
1#
b00100110 '
#80
0#
#81
1#
b00100111 '
#82
0#
#83
1#
b00101000 '
#84
0#
#85
1#
b00101001 '
#86
0#
#87
1#
b00101010 '
#88
0#
#89
1#
b00101011 '
#90
0#
#91
1#
b00101100 '
#92
0#
#93
1#
b00101101 '
#94
0#
#95
1#
b00101110 '
#96
0#
#97
1#
b00101111 '
#98
0#
#99
1#
b00110000 '
#100
0#
#101
1#
b00110001 '
#102
0#
#103
1#
b00110010 '
#104
0#
#105
1#
b00110011 '
#106
0#
#107
1#
b00110100 '
#108
0#
#109
1#
b00110101 '
#110
0#
#111
1#
b00110110 '
#112
0#
#113
1#
b00110111 '
#114
0#
#115
1#
b00111000 '
#116
0#
#117
1#
b00111001 '
#118
0#
#119
1#
b00111010 '
#120
0#
#121
1#
b00111011 '
#122
0#
#123
1#
b00111100 '
#124
0#
1%
#125
1#
b00010011 '
#126
0#
0%
#127
1#
b00010100 '
#128
0#
#129
1#
b00010101 '
#130
0#
#131
1#
b00010110 '
#132
0#
#133
1#
b00010111 '
#134
0#
#135
1#
b00011000 '
#136
0#
#137
1#
b00011001 '
#138
0#
#139
1#
b00011010 '
#140
0#
#141
1#
b00011011 '
#142
0#
#143
1#
b00011100 '
#144
0#
#145
1#
b00011101 '
#146
0#
#147
1#
b00011110 '
#148
0#
#149
1#
b00011111 '
#150
0#
#151
1#
b00100000 '
#152
0#
#153
1#
b00100001 '
#154
0#
#155
1#
b00100010 '
#156
0#
#157
1#
b00100011 '
#158
0#
#159
1#
b00100100 '
#160
0#
#161
1#
b00100101 '
#162
0#
#163
1#
b00100110 '
#164
0#
#165
1#
b00100111 '
#166
0#
#167
1#
b00101000 '
#168
0#
#169
1#
b00101001 '
#170
0#
#171
1#
b00101010 '
#172
0#
#173
1#
b00101011 '
#174
0#
#175
1#
b00101100 '
#176
0#
#177
1#
b00101101 '
#178
0#
#179
1#
b00101110 '
#180
0#
1%
#181
1#
b00010011 '
#182
0#
0%
#183
1#
b00010100 '
#184
0#
#185
1#
b00010101 '
#186
0#
#187
1#
b00010110 '
#188
0#
#189
1#
b00010111 '
#190
0#
#191
1#
b00011000 '
#192
0#
#193
1#
b00011001 '
#194
0#
#195
1#
b00011010 '
#196
0#
#197
1#
b00011011 '
#198
0#
#199
1#
b00011100 '
#200
0#
#201
1#
b00011101 '
#202
0#
#203
1#
b00011110 '
#204
0#
#205
1#
b00011111 '
#206
0#
#207
1#
b00100000 '
#208
0#
#209
1#
b00100001 '
#210
0#
#211
1#
b00100010 '
#212
0#
#213
1#
b00100011 '
#214
0#
#215
1#
b00100100 '
#216
0#
1%
#217
1#
b00010011 '
#218
0#
0%
#219
1#
b00010100 '
#220
0#
#221
1#
b00010101 '
#222
0#
#223
1#
b00010110 '
#224
0#
#225
1#
b00010111 '
#226
0#
#227
1#
b00011000 '
#228
0#
#229
1#
b00011001 '
#230
0#
#231
1#
b00011010 '
#232
0#
#233
1#
b00011011 '
#234
0#
#235
1#
b00011100 '
#236
0#
#237
1#
b00011101 '
#238
0#
#239
1#
b00011110 '
#240
0#
#241
1#
b00011111 '
#242
0#
#243
1#
b00100000 '
#244
0#
#245
1#
b00100001 '
#246
0#
#247
1#
b00100010 '
#248
0#
#249
1#
b00100011 '
#250
0#
#251
1#
b00100100 '
#252
0#
#253
1#
b00100101 '
#254
0#
#255
1#
b00100110 '
#256
0#
#257
1#
b00100111 '
#258
0#
#259
1#
b00101000 '
#260
0#
#261
1#
b00101001 '
#262
0#
#263
1#
b00101010 '
#264
0#
#265
1#
b00101011 '
#266
0#
#267
1#
b00101100 '
#268
0#
#269
1#
b00101101 '
#270
0#
#271
1#
b00101110 '
#272
0#
#273
1#
b00101111 '
#274
0#
#275
1#
b00110000 '
#276
0#
#277
1#
b00110001 '
#278
0#
#279
1#
b00110010 '
#280
0#
#281
1#
b00110011 '
#282
0#
#283
1#
b00110100 '
#284
0#
#285
1#
b00110101 '
#286
0#
#287
1#
b00110110 '
#288
0#
#289
1#
b00110111 '
#290
0#
#291
1#
b00111000 '
#292
0#
#293
1#
b00111001 '
#294
0#
#295
1#
b00111010 '
#296
0#
#297
1#
b00111011 '
#298
0#
#299
1#
b00111100 '
#300
0#
#301
1#
b00111101 '
#302
0#
#303
1#
b00111110 '
#304
0#
#305
1#
b00111111 '
#306
0#
#307
1#
b01000000 '
#308
0#
#309
1#
b01000001 '
#310
0#
#311
1#
b01000010 '
#312
0#
#313
1#
b01000011 '
#314
0#
#315
1#
b01000100 '
#316
0#
#317
1#
b01000101 '
#318
0#
#319
1#
b01000110 '
#320
0#
#321
1#
b01000111 '
#322
0#
#323
1#
b01001000 '
#324
0#
#325
1#
b01001001 '
#326
0#
#327
1#
b01001010 '
#328
0#
#329
1#
b01001011 '
#330
0#
#331
1#
b01001100 '
#332
0#
#333
1#
b01001101 '
#334
0#
#335
1#
b01001110 '
#336
0#
#337
1#
b01001111 '
#338
0#
#339
1#
b01010000 '
#340
0#
#341
1#
b01010001 '
#342
0#
#343
1#
b01010010 '
#344
0#
#345
1#
b01010011 '
#346
0#
#347
1#
b01010100 '
#348
0#
#349
1#
b01010101 '
#350
0#
#351
1#
b01010110 '
#352
0#
#353
1#
b01010111 '
#354
0#
#355
1#
b01011000 '
#356
0#
#357
1#
b01011001 '
#358
0#
#359
1#
b01011010 '
#360
0#
#361
1#
b01011011 '
#362
0#
#363
1#
b01011100 '
#364
0#
#365
1#
b01011101 '
#366
0#
#367
1#
b01011110 '
#368
0#
#369
1#
b01011111 '
#370
0#
#371
1#
b01100000 '
#372
0#
#373
1#
b01100001 '
#374
0#
#375
1#
b01100010 '
#376
0#
#377
1#
b01100011 '
#378
0#
#379
1#
b01100100 '
#380
0#
#381
1#
b01100101 '
#382
0#
#383
1#
b01100110 '
#384
0#
#385
1#
b01100111 '
#386
0#
#387
1#
b01101000 '
#388
0#
#389
1#
b01101001 '
#390
0#
#391
1#
b01101010 '
#392
0#
#393
1#
b01101011 '
#394
0#
#395
1#
b01101100 '
#396
0#
#397
1#
b01101101 '
#398
0#
#399
1#
b01101110 '
#400
0#
b00010010 &
#401
1#
b01101111 '
#402
0#
b00010001 &
#403
1#
b01110000 '
#404
0#
b00001111 &
#405
1#
b01110001 '
#406
0#
b00001011 &
#407
1#
b01110010 '
#408
0#
b00001000 &
#409
1#
b01110011 '
#410
0#
b00000110 &
#411
1#
b01110100 '
#412
0#
#413
1#
b01110101 '
#414
0#
#415
1#
b01110110 '
#416
0#
#417
1#
b01110111 '
#418
0#
#419
1#
b01111000 '
#420
0#
#421
1#
b01111001 '
#422
0#
#423
1#
b01111010 '
#424
0#
#425
1#
b01111011 '
#426
0#
#427
1#
b01111100 '
#428
0#
#429
1#
b01111101 '
#430
0#
b00000101 &
#431
1#
b01111110 '
#432
0#
b00000011 &
#433
1#
b01111111 '
#434
0#
b00000010 &
#435
1#
b10000000 '
#436
0#
b00000000 &
#437
1#
b10000001 '
#438
0#
#439
1#
b10000010 '
#440
0#
#441
1#
b10000011 '
#442
0#
#443
1#
b10000100 '
#444
0#
#445
1#
b10000101 '
#446
0#
#447
1#
b10000110 '
#448
0#
#449
1#
b10000111 '
#450
0#
#451
1#
b10001000 '
#452
0#
#453
1#
b10001001 '
#454
0#
#455
1#
b10001010 '
#456
0#
#457
1#
b10001011 '
#458
0#
#459
1#
b10001100 '
#460
0#
#461
1#
b10001101 '
#462
0#
#463
1#
b10001110 '
#464
0#
#465
1#
b10001111 '
#466
0#
#467
1#
b10010000 '
#468
0#
#469
1#
b10010001 '
#470
0#
#471
1#
b10010010 '
#472
0#
#473
1#
b10010011 '
#474
0#
#475
1#
b10010100 '
#476
0#
#477
1#
b10010101 '
#478
0#
#479
1#
b10010110 '
#480
0#
1%
#481
1#
b00000000 '
#482
0#
0%
#483
1#
b00000001 '
#484
0#
#485
1#
b00000010 '
#486
0#
#487
1#
b00000011 '
#488
0#
#489
1#
b00000100 '
#490
0#
#491
1#
b00000101 '
#492
0#
#493
1#
b00000110 '
#494
0#
#495
1#
b00000111 '
#496
0#
#497
1#
b00001000 '
#498
0#
#499
1#
b00001001 '
#500
0#
#501
1#
b00001010 '
#502
0#
#503
1#
b00001011 '
#504
0#
#505
1#
b00001100 '
#506
0#
#507
1#
b00001101 '
#508
0#
#509
1#
b00001110 '
#510
0#
#511
1#
b00001111 '
#512
0#
#513
1#
b00010000 '
#514
0#
#515
1#
b00010001 '
#516
0#
1%
#517
1#
b00000000 '
#518
0#
0%
#519
1#
b00000001 '
#520
0#
#521
1#
b00000010 '
#522
0#
#523
1#
b00000011 '
#524
0#
#525
1#
b00000100 '
#526
0#
#527
1#
b00000101 '
#528
0#
#529
1#
b00000110 '
#530
0#
#531
1#
b00000111 '
#532
0#
#533
1#
b00001000 '
#534
0#
#535
1#
b00001001 '
#536
0#
#537
1#
b00001010 '
#538
0#
#539
1#
b00001011 '
#540
0#
#541
1#
b00001100 '
#542
0#
#543
1#
b00001101 '
#544
0#
#545
1#
b00001110 '
#546
0#
1%
#547
1#
b00000000 '
#548
0#
0%
#549
1#
b00000001 '
#550
0#
#551
1#
b00000010 '
#552
0#
#553
1#
b00000011 '
#554
0#
#555
1#
b00000100 '
#556
0#
#557
1#
b00000101 '
#558
0#
#559
1#
b00000110 '
#560
0#
#561
1#
b00000111 '
#562
0#
#563
1#
b00001000 '
#564
0#
#565
1#
b00001001 '
#566
0#
#567
1#
b00001010 '
#568
0#
1%
#569
1#
b00000000 '
#570
0#
0%
#571
1#
b00000001 '
#572
0#
#573
1#
b00000010 '
#574
0#
#575
1#
b00000011 '
#576
0#
#577
1#
b00000100 '
#578
0#
#579
1#
b00000101 '
#580
0#
#581
1#
b00000110 '
#582
0#
#583
1#
b00000111 '
#584
0#
#585
1#
b00001000 '
#586
0#
1%
#587
1#
b00000000 '
#588
0#
0%
#589
1#
b00000001 '
#590
0#
#591
1#
b00000010 '
#592
0#
#593
1#
b00000011 '
#594
0#
#595
1#
b00000100 '
#596
0#
#597
1#
b00000101 '
#598
0#
#599
1#
b00000110 '
#600
0#
1%
#601
1#
b00000000 '
#602
0#
0%
#603
1#
b00000001 '
#604
0#
#605
1#
b00000010 '
#606
0#
#607
1#
b00000011 '
#608
0#
#609
1#
b00000100 '
#610
0#
#611
1#
b00000101 '
#612
0#
#613
1#
b00000110 '
#614
0#
#615
1#
b00000111 '
#616
0#
#617
1#
b00001000 '
#618
0#
#619
1#
b00001001 '
#620
0#
1%
#621
1#
b00000000 '
#622
0#
0%
#623
1#
b00000001 '
#624
0#
#625
1#
b00000010 '
#626
0#
#627
1#
b00000011 '
#628
0#
1%
#629
1#
b00000000 '
#630
0#
0%
#631
1#
b00000001 '
#632
0#
#633
1#
b00000010 '
#634
0#
#635
1#
b00000011 '
#636
0#
#637
1#
b00000100 '
#638
0#
1%
#639
1#
b00000000 '
#640
0#
0%
#641
1#
b00000001 '
#642
0#
#643
1#
b00000010 '
#644
0#
#645
1#
b00000011 '
#646
0#
#647
1#
b00000100 '
#648
0#
#649
1#
b00000101 '
#650
0#
#651
1#
b00000110 '
#652
0#
#653
1#
b00000111 '
#654
0#
#655
1#
b00001000 '
#656
0#
1%
#657
1#
b00000000 '
#658
0#
0%
#659
1#
b00000001 '
#660
0#
#661
1#
b00000010 '
#662
0#
#663
1#
b00000011 '
#664
0#
#665
1#
b00000100 '
#666
0#
#667
1#
b00000101 '
#668
0#
#669
1#
b00000110 '
#670
0#
#671
1#
b00000111 '
#672
0#
#673
1#
b00001000 '
#674
0#
#675
1#
b00001001 '
#676
0#
#677
1#
b00001010 '
#678
0#
#679
1#
b00001011 '
#680
0#
#681
1#
b00001100 '
#682
0#
#683
1#
b00001101 '
#684
0#
#685
1#
b00001110 '
#686
0#
#687
1#
b00001111 '
#688
0#
#689
1#
b00010000 '
#690
0#
#691
1#
b00010001 '
#692
0#
#693
1#
b00010010 '
#694
0#
#695
1#
b00010011 '
#696
0#
#697
1#
b00010100 '
#698
0#
#699
1#
b00010101 '
#700
0#
#701
1#
b00010110 '
#702
0#
#703
1#
b00010111 '
#704
0#
#705
1#
b00011000 '
#706
0#
#707
1#
b00011001 '
#708
0#
#709
1#
b00011010 '
#710
0#
#711
1#
b00011011 '
#712
0#
#713
1#
b00011100 '
#714
0#
#715
1#
b00011101 '
#716
0#
#717
1#
b00011110 '
#718
0#
#719
1#
b00011111 '
#720
0#
#721
1#
b00100000 '
#722
0#
#723
1#
b00100001 '
#724
0#
#725
1#
b00100010 '
#726
0#
#727
1#
b00100011 '
#728
0#
#729
1#
b00100100 '
#730
0#
#731
1#
b00100101 '
#732
0#
#733
1#
b00100110 '
#734
0#
#735
1#
b00100111 '
#736
0#
#737
1#
b00101000 '
#738
0#
#739
1#
b00101001 '
#740
0#
#741
1#
b00101010 '
#742
0#
#743
1#
b00101011 '
#744
0#
#745
1#
b00101100 '
#746
0#
#747
1#
b00101101 '
#748
0#
1%
#749
1#
b00000000 '
#750
0#
0%
#751
1#
b00000001 '
#752
0#
#753
1#
b00000010 '
#754
0#
#755
1#
b00000011 '
#756
0#
#757
1#
b00000100 '
#758
0#
#759
1#
b00000101 '
#760
0#
#761
1#
b00000110 '
#762
0#
#763
1#
b00000111 '
#764
0#
#765
1#
b00001000 '
#766
0#
#767
1#
b00001001 '
#768
0#
#769
1#
b00001010 '
#770
0#
#771
1#
b00001011 '
#772
0#
#773
1#
b00001100 '
#774
0#
#775
1#
b00001101 '
#776
0#
#777
1#
b00001110 '
#778
0#
#779
1#
b00001111 '
#780
0#
#781
1#
b00010000 '
#782
0#
#783
1#
b00010001 '
#784
0#
#785
1#
b00010010 '
#786
0#
#787
1#
b00010011 '
#788
0#
#789
1#
b00010100 '
#790
0#
#791
1#
b00010101 '
#792
0#
#793
1#
b00010110 '
#794
0#
1%
#795
1#
b00000000 '
#796
0#
0%
#797
1#
b00000001 '
#798
0#
#799
1#
b00000010 '
#800
0#
#801
1#
b00000011 '
#802
0#
#803
1#
b00000100 '
#804
0#
#805
1#
b00000101 '
#806
0#
#807
1#
b00000110 '
#808
0#
#809
1#
b00000111 '
#810
0#
#811
1#
b00001000 '
#812
0#
#813
1#
b00001001 '
#814
0#
#815
1#
b00001010 '
#816
0#
#817
1#
b00001011 '
#818
0#
1%
#819
1#
b00000000 '
#820
0#
0%
#821
1#
b00000001 '
#822
0#
#823
1#
b00000010 '
#824
0#
#825
1#
b00000011 '
#826
0#
#827
1#
b00000100 '
#828
0#
#829
1#
b00000101 '
#830
0#
1%
#831
1#
b00000000 '
#832
0#
0%
#833
1#
b00000001 '
#834
0#
#835
1#
b00000010 '
#836
0#
#837
1#
b00000011 '
#838
0#
#839
1#
b00000100 '
#840
0#
1%
#841
1#
b00000000 '
#842
0#
0%
#843
1#
b00000001 '
#844
0#
#845
1#
b00000010 '
#846
0#
#847
1#
b00000011 '
#848
0#
#849
1#
b00000100 '
#850
0#
#851
1#
b00000101 '
#852
0#
1%
#853
1#
b00000000 '
#854
0#
0%
#855
1#
b00000001 '
#856
0#
#857
1#
b00000010 '
#858
0#
#859
1#
b00000011 '
#860
0#
#861
1#
b00000100 '
#862
0#
#863
1#
b00000101 '
#864
0#
1%
#865
1#
b00000000 '
#866
0#
0%
#867
1#
b00000001 '
#868
0#
#869
1#
b00000010 '
#870
0#
#871
1#
b00000011 '
#872
0#
#873
1#
b00000100 '
#874
0#
1%
#875
1#
b00000000 '
#876
0#
0%
#877
1#
b00000001 '
#878
0#
#879
1#
b00000010 '
#880
0#
#881
1#
b00000011 '
#882
0#
#883
1#
b00000100 '
#884
0#
#885
1#
b00000101 '
#886
0#
1%
#887
1#
b00000000 '
#888
0#
0%
#889
1#
b00000001 '
#890
0#
#891
1#
b00000010 '
#892
0#
#893
1#
b00000011 '
#894
0#
#895
1#
b00000100 '
#896
0#
#897
1#
b00000101 '
#898
0#
1%
#899
1#
b00000000 '
#900
0#
0%
#901
1#
b00000001 '
#902
0#
#903
1#
b00000010 '
#904
0#
#905
1#
b00000011 '
#906
0#
#907
1#
b00000100 '
#908
0#
#909
1#
b00000101 '
#910
0#
#911
1#
b00000110 '
#912
0#
#913
1#
b00000111 '
#914
0#
#915
1#
b00001000 '
#916
0#
#917
1#
b00001001 '
#918
0#
#919
1#
b00001010 '
#920
0#
#921
1#
b00001011 '
#922
0#
#923
1#
b00001100 '
#924
0#
#925
1#
b00001101 '
#926
0#
#927
1#
b00001110 '
#928
0#
#929
1#
b00001111 '
#930
0#
#931
1#
b00010000 '
#932
0#
#933
1#
b00010001 '
#934
0#
#935
1#
b00010010 '
#936
0#
#937
1#
b00010011 '
#938
0#
#939
1#
b00010100 '
#940
0#
#941
1#
b00010101 '
#942
0#
#943
1#
b00010110 '
#944
0#
#945
1#
b00010111 '
#946
0#
#947
1#
b00011000 '
#948
0#
#949
1#
b00011001 '
#950
0#
#951
1#
b00011010 '
#952
0#
#953
1#
b00011011 '
#954
0#
#955
1#
b00011100 '
#956
0#
#957
1#
b00011101 '
#958
0#
#959
1#
b00011110 '
#960
0#
b00000001 &
#961
1#
b00011111 '
#962
0#
#963
1#
b00100000 '
#964
0#
#965
1#
b00100001 '
#966
0#
b00000010 &
#967
1#
b00100010 '
#968
0#
b00000011 &
#969
1#
b00100011 '
#970
0#
b00000100 &
#971
1#
b00100100 '
#972
0#
b00000101 &
#973
1#
b00100101 '
#974
0#
b00000110 &
#975
1#
b00100110 '
#976
0#
#977
1#
b00100111 '
#978
0#
b00000111 &
#979
1#
b00101000 '
#980
0#
#981
1#
b00101001 '
#982
0#
#983
1#
b00101010 '
#984
0#
#985
1#
b00101011 '
#986
0#
b00001000 &
#987
1#
b00101100 '
#988
0#
#989
1#
b00101101 '
#990
0#
#991
1#
b00101110 '
#992
0#
#993
1#
b00101111 '
#994
0#
#995
1#
b00110000 '
#996
0#
#997
1#
b00110001 '
#998
0#
b00001001 &
#999
1#
b00110010 '
#1000
0#
#1001
1#
b00110011 '
#1002
0#
b00001010 &
#1003
1#
b00110100 '
#1004
0#
b00001011 &
#1005
1#
b00110101 '
#1006
0#
b00001110 &
#1007
1#
b00110110 '
#1008
0#
b00010000 &
#1009
1#
b00110111 '
#1010
0#
b00010100 &
#1011
1#
b00111000 '
#1012
0#
b00010101 &
#1013
1#
b00111001 '
#1014
0#
b00010111 &
#1015
1#
b00111010 '
#1016
0#
b00011000 &
#1017
1#
b00111011 '
#1018
0#
#1019
1#
b00111100 '
#1020
0#
#1021
1#
b00111101 '
#1022
0#
#1023
1#
b00111110 '
#1024
0#
#1025
1#
b00111111 '
#1026
0#
#1027
1#
b01000000 '
#1028
0#
#1029
1#
b01000001 '
#1030
0#
#1031
1#
b01000010 '
#1032
0#
#1033
1#
b01000011 '
#1034
0#
#1035
1#
b01000100 '
#1036
0#
#1037
1#
b01000101 '
#1038
0#
#1039
1#
b01000110 '
#1040
0#
#1041
1#
b01000111 '
#1042
0#
#1043
1#
b01001000 '
#1044
0#
#1045
1#
b01001001 '
#1046
0#
#1047
1#
b01001010 '
#1048
0#
#1049
1#
b01001011 '
#1050
0#
#1051
1#
b01001100 '
#1052
0#
b00011001 &
#1053
1#
b01001101 '
#1054
0#
b00011010 &
#1055
1#
b01001110 '
#1056
0#
b00011011 &
#1057
1#
b01001111 '
#1058
0#
b00011110 &
#1059
1#
b01010000 '
#1060
0#
b00100010 &
#1061
1#
b01010001 '
#1062
0#
b00100110 &
#1063
1#
b01010010 '
#1064
0#
#1065
1#
b01010011 '
#1066
0#
#1067
1#
b01010100 '
#1068
0#
#1069
1#
b01010101 '
#1070
0#
#1071
1#
b01010110 '
#1072
0#
#1073
1#
b01010111 '
#1074
0#
#1075
1#
b01011000 '
#1076
0#
#1077
1#
b01011001 '
#1078
0#
#1079
1#
b01011010 '
#1080
0#
#1081
1#
b01011011 '
#1082
0#
#1083
1#
b01011100 '
#1084
0#
#1085
1#
b01011101 '
#1086
0#
#1087
1#
b01011110 '
#1088
0#
#1089
1#
b01011111 '
#1090
0#
#1091
1#
b01100000 '
#1092
0#
#1093
1#
b01100001 '
#1094
0#
#1095
1#
b01100010 '
#1096
0#
#1097
1#
b01100011 '
#1098
0#
#1099
1#
b01100100 '
#1100
0#
#1101
1#
b01100101 '
#1102
0#
#1103
1#
b01100110 '
#1104
0#
#1105
1#
b01100111 '
#1106
0#
1%
#1107
1#
b00100110 '
#1108
0#
0%
#1109
1#
b00100111 '
#1110
0#
#1111
1#
b00101000 '
#1112
0#
#1113
1#
b00101001 '
#1114
0#
#1115
1#
b00101010 '
#1116
0#
#1117
1#
b00101011 '
#1118
0#
#1119
1#
b00101100 '
#1120
0#
#1121
1#
b00101101 '
#1122
0#
#1123
1#
b00101110 '
#1124
0#
#1125
1#
b00101111 '
#1126
0#
#1127
1#
b00110000 '
#1128
0#
#1129
1#
b00110001 '
#1130
0#
#1131
1#
b00110010 '
#1132
0#
#1133
1#
b00110011 '
#1134
0#
#1135
1#
b00110100 '
#1136
0#
#1137
1#
b00110101 '
#1138
0#
#1139
1#
b00110110 '
#1140
0#
#1141
1#
b00110111 '
#1142
0#
#1143
1#
b00111000 '
#1144
0#
#1145
1#
b00111001 '
#1146
0#
#1147
1#
b00111010 '
#1148
0#
#1149
1#
b00111011 '
#1150
0#
#1151
1#
b00111100 '
#1152
0#
#1153
1#
b00111101 '
#1154
0#
#1155
1#
b00111110 '
#1156
0#
#1157
1#
b00111111 '
#1158
0#
#1159
1#
b01000000 '
#1160
0#
#1161
1#
b01000001 '
#1162
0#
#1163
1#
b01000010 '
#1164
0#
#1165
1#
b01000011 '
#1166
0#
#1167
1#
b01000100 '
#1168
0#
#1169
1#
b01000101 '
#1170
0#
b00100111 &
#1171
1#
b01000110 '
#1172
0#
#1173
1#
b01000111 '
#1174
0#
b00101001 &
#1175
1#
b01001000 '
#1176
0#
b00101011 &
#1177
1#
b01001001 '
#1178
0#
b00101101 &
#1179
1#
b01001010 '
#1180
0#
b00101111 &
#1181
1#
b01001011 '
#1182
0#
b00110010 &
#1183
1#
b01001100 '
#1184
0#
b00110011 &
#1185
1#
b01001101 '
#1186
0#
#1187
1#
b01001110 '
#1188
0#
#1189
1#
b01001111 '
#1190
0#
#1191
1#
b01010000 '
#1192
0#
#1193
1#
b01010001 '
#1194
0#
#1195
1#
b01010010 '
#1196
0#
#1197
1#
b01010011 '
#1198
0#
#1199
1#
b01010100 '
#1200
0#
#1201
1#
b01010101 '
#1202
0#
#1203
1#
b01010110 '
#1204
0#
#1205
1#
b01010111 '
#1206
0#
b00110101 &
#1207
1#
b01011000 '
#1208
0#
b00111010 &
#1209
1#
b01011001 '
#1210
0#
b00111100 &
#1211
1#
b01011010 '
#1212
0#
b00111101 &
#1213
1#
b01011011 '
#1214
0#
#1215
1#
b01011100 '
#1216
0#
#1217
1#
b01011101 '
#1218
0#
#1219
1#
b01011110 '
#1220
0#
#1221
1#
b01011111 '
#1222
0#
#1223
1#
b01100000 '
#1224
0#
#1225
1#
b01100001 '
#1226
0#
#1227
1#
b01100010 '
#1228
0#
#1229
1#
b01100011 '
#1230
0#
b00111111 &
#1231
1#
b01100100 '
#1232
0#
b01000010 &
#1233
1#
b01100101 '
#1234
0#
b01000111 &
#1235
1#
b01100110 '
#1236
0#
#1237
1#
b01100111 '
#1238
0#
#1239
1#
b01101000 '
#1240
0#
#1241
1#
b01101001 '
#1242
0#
#1243
1#
b01101010 '
#1244
0#
#1245
1#
b01101011 '
#1246
0#
#1247
1#
b01101100 '
#1248
0#
#1249
1#
b01101101 '
#1250
0#
#1251
1#
b01101110 '
#1252
0#
#1253
1#
b01101111 '
#1254
0#
b01001001 &
#1255
1#
b01110000 '
#1256
0#
b01001110 &
#1257
1#
b01110001 '
#1258
0#
b01001111 &
#1259
1#
b01110010 '
#1260
0#
#1261
1#
b01110011 '
#1262
0#
#1263
1#
b01110100 '
#1264
0#
#1265
1#
b01110101 '
#1266
0#
#1267
1#
b01110110 '
#1268
0#
#1269
1#
b01110111 '
#1270
0#
#1271
1#
b01111000 '
#1272
0#
#1273
1#
b01111001 '
#1274
0#
#1275
1#
b01111010 '
#1276
0#
#1277
1#
b01111011 '
#1278
0#
b01010001 &
#1279
1#
b01111100 '
#1280
0#
b01010101 &
#1281
1#
b01111101 '
#1282
0#
b01011000 &
#1283
1#
b01111110 '
#1284
0#
#1285
1#
b01111111 '
#1286
0#
#1287
1#
b10000000 '
#1288
0#
#1289
1#
b10000001 '
#1290
0#
#1291
1#
b10000010 '
#1292
0#
#1293
1#
b10000011 '
#1294
0#
#1295
1#
b10000100 '
#1296
0#
#1297
1#
b10000101 '
#1298
0#
#1299
1#
b10000110 '
#1300
0#
#1301
1#
b10000111 '
#1302
0#
#1303
1#
b10001000 '
#1304
0#
#1305
1#
b10001001 '
#1306
0#
#1307
1#
b10001010 '
#1308
0#
#1309
1#
b10001011 '
#1310
0#
#1311
1#
b10001100 '
#1312
0#
#1313
1#
b10001101 '
#1314
0#
#1315
1#
b10001110 '
#1316
0#
#1317
1#
b10001111 '
#1318
0#
#1319
1#
b10010000 '
#1320
0#
#1321
1#
b10010001 '
#1322
0#
1%
#1323
1#
b01011000 '
#1324
0#
0%
#1325
1#
b01011001 '
#1326
0#
#1327
1#
b01011010 '
#1328
0#
#1329
1#
b01011011 '
#1330
0#
#1331
1#
b01011100 '
#1332
0#
#1333
1#
b01011101 '
#1334
0#
#1335
1#
b01011110 '
#1336
0#
#1337
1#
b01011111 '
#1338
0#
#1339
1#
b01100000 '
#1340
0#
#1341
1#
b01100001 '
#1342
0#
#1343
1#
b01100010 '
#1344
0#
#1345
1#
b01100011 '
#1346
0#
#1347
1#
b01100100 '
#1348
0#
#1349
1#
b01100101 '
#1350
0#
#1351
1#
b01100110 '
#1352
0#
#1353
1#
b01100111 '
#1354
0#
#1355
1#
b01101000 '
#1356
0#
#1357
1#
b01101001 '
#1358
0#
#1359
1#
b01101010 '
#1360
0#
#1361
1#
b01101011 '
#1362
0#
#1363
1#
b01101100 '
#1364
0#
#1365
1#
b01101101 '
#1366
0#
#1367
1#
b01101110 '
#1368
0#
#1369
1#
b01101111 '
#1370
0#
#1371
1#
b01110000 '
#1372
0#
#1373
1#
b01110001 '
#1374
0#
#1375
1#
b01110010 '
#1376
0#
#1377
1#
b01110011 '
#1378
0#
#1379
1#
b01110100 '
#1380
0#
#1381
1#
b01110101 '
#1382
0#
#1383
1#
b01110110 '
#1384
0#
#1385
1#
b01110111 '
#1386
0#
#1387
1#
b01111000 '
#1388
0#
#1389
1#
b01111001 '
#1390
0#
#1391
1#
b01111010 '
#1392
0#
#1393
1#
b01111011 '
#1394
0#
#1395
1#
b01111100 '
#1396
0#
#1397
1#
b01111101 '
#1398
0#
#1399
1#
b01111110 '
#1400
0#
#1401
1#
b01111111 '
#1402
0#
#1403
1#
b10000000 '
#1404
0#
#1405
1#
b10000001 '
#1406
0#
#1407
1#
b10000010 '
#1408
0#
#1409
1#
b10000011 '
#1410
0#
#1411
1#
b10000100 '
#1412
0#
#1413
1#
b10000101 '
#1414
0#
#1415
1#
b10000110 '
#1416
0#
#1417
1#
b10000111 '
#1418
0#
#1419
1#
b10001000 '
#1420
0#
#1421
1#
b10001001 '
#1422
0#
#1423
1#
b10001010 '
#1424
0#
#1425
1#
b10001011 '
